{
  "fetched_at": "2026-02-12T17:20:26.451121",
  "lat": 52.289597,
  "lon": 104.280586,
  "endpoint": "weather",
  "data": {
    "coord": {
      "lon": 104.2964,
      "lat": 52.2978
    },
    "weather": [
      {
        "id": 800,
        "main": "Clear",
        "description": "ясно",
        "icon": "01d"
      }
    ],
    "base": "stations",
    "main": {
      "temp": -0.57,
      "feels_like": -0.57,
      "temp_min": -0.57,
      "temp_max": -0.57,
      "pressure": 1013,
      "humidity": 55,
      "sea_level": 1013,
      "grnd_level": 961
    },
    "visibility": 10000,
    "wind": {
      "speed": 1,
      "deg": 10
    },
    "clouds": {
      "all": 0
    },
    "dt": 1770887850,
    "sys": {
      "type": 1,
      "id": 8891,
      "country": "RU",
      "sunrise": 1770855927,
      "sunset": 1770890930
    },
    "timezone": 28800,
    "id": 2023469,
    "name": "Иркутск",
    "cod": 200
  }
}